polus/__init__.py
polus/bert_utils.py
polus/callbacks.py
polus/core.py
polus/data.py
polus/hpo.py
polus/layers.py
polus/losses.py
polus/metrics.py
polus/models.py
polus/schedulers.py
polus/training.py
polus/utils.py
polus/experimental/__init__.py
polus/experimental/callbacks.py
polus/experimental/data.py
polus/experimental/layers.py
polus/experimental/metrics.py
polus/experimental/models.py
polus/experimental/training.py
polus/experimental/utils.py
polus/ir/__init__.py
polus/ir/training.py
polus/ner/__init__.py
polus/ner/bio.py
polus/ner/elements.py
polus/ner/metrics.py
polus/ner/models.py
polus/ner/utils.py
poluslib/__init__.py
poluslib/callbacks.py
poluslib/core.py
poluslib/data.py
poluslib/layers.py
poluslib/metrics.py
poluslib/models.py
poluslib/training.py
poluslib/utils.py
polus-0.1.8.dist-info/METADATA
polus-0.1.8.dist-info/WHEEL
polus-0.1.8.dist-info/top_level.txt
polus-0.1.8.dist-info/RECORD
